data_to_html/__init__.py
data_to_html/main.py
data_to_html_connosieurofdoom-0.0.0.1.dist-info/LICENSE
data_to_html_connosieurofdoom-0.0.0.1.dist-info/METADATA
data_to_html_connosieurofdoom-0.0.0.1.dist-info/WHEEL
data_to_html_connosieurofdoom-0.0.0.1.dist-info/top_level.txt
data_to_html_connosieurofdoom-0.0.0.1.dist-info/RECORD
