Metadata-Version: 2.1
Name: data-to-html-connosieurofdoom
Version: 0.0.0.1
Summary: Convert Dataframe to html elements
Home-page: https://github.com/connosieurofdoom/data_to_html
Author: Example Author
Author-email: shreyasajitrajendra@gmail.com
License: UNKNOWN
Platform: UNKNOWN
Classifier: Programming Language :: Python :: 3
Classifier: License :: OSI Approved :: GNU General Public License (GPL)
Classifier: Operating System :: OS Independent
Requires-Python: >=3.6
